{
    "ragweed allergen extract": "Allergy & Cold",
    "grass pollens allergen extract": "Allergy & Cold",
    "Timothy grass pollen allergen extract": "Allergy & Cold",
    "house dust mite immunotherapy": "Allergy & Cold",
    "peanut oral allergen powder": "Allergy & Cold",
    "azelastine": "Allergy & Cold",
    "ipratropium intranasal": "Allergy & Cold",
    "azelastine/fluticasone intranasal": "Allergy & Cold",
    "cromolyn sodium, intranasal": "Allergy & Cold",
    "olopatadine intranasal": "Allergy & Cold",
    "olopatadine intranasal/mometasone, intranasal": "Allergy & Cold",
    "acetaminophen/chlorpheniramine/dextromethorphan": "Allergy & Cold",
    "acetaminophen/diphenhydramine/dextromethorphan": "Allergy & Cold",
    "aspirin/chlorpheniramine/dextromethorphan": "Allergy & Cold",
    "acetaminophen/chlorpheniramine/dextromethorphan/phenylephrine": "Allergy & Cold",
    "acetaminophen/doxylamine/dextromethorphan/phenylephrine": "Allergy & Cold",
    "aspirin/chlorpheniramine/dextromethorphan/phenylephrine": "Allergy & Cold",
    "acetaminophen/dextromethorphan/phenylephrine/guaifenesin": "Allergy & Cold",
    "acetaminophen/dextromethorphan/pseudoephedrine/guaifenesin": "Allergy & Cold",
    "acetaminophen/dextromethorphan/phenylephrine": "Allergy & Cold",
    "acetaminophen/dextromethorphan/pseudoephedrine": "Allergy & Cold",
    "acetaminophen/phenylephrine": "Allergy & Cold",
    "acetaminophen/pseudoephedrine": "Allergy & Cold",
    "ibuprofen/pseudoephedrine": "Allergy & Cold",
    "ibuprofen/phenylephrine": "Allergy & Cold",
    "naproxen/pseudoephedrine": "Allergy & Cold",
    "acetaminophen/phenylephrine/guaifenesin": "Allergy & Cold",
    "acetaminophen/pseudoephedrine/guaifenesin": "Allergy & Cold",
    "acetaminophen/guaifenesin": "Allergy & Cold",
    "chlorpheniramine/dextromethorphan": "Allergy & Cold",
    "brompheniramine/dextromethorphan/pseudoephedrine": "Allergy & Cold",
    "brompheniramine/dextromethorphan/phenylephrine": "Allergy & Cold",
    "chlorpheniramine/dextromethorphan/pseudoephedrine": "Allergy & Cold",
    "chlorpheniramine/pseudoephedrine": "Allergy & Cold",
    "acrivastine/pseudoephedrine": "Allergy & Cold",
    "chlorpheniramine/phenylephrine": "Allergy & Cold",
    "pseudoephedrine/loratadine": "Allergy & Cold",
    "pseudoephedrine/fexofenadine": "Allergy & Cold",
    "brompheniramine/pseudoephedrine": "Allergy & Cold",
    "brompheniramine/phenylephrine": "Allergy & Cold",
    "cetirizine/pseudoephedrine": "Allergy & Cold",
    "diphenhydramine/phenylephrine": "Allergy & Cold",
    "pseudoephedrine/desloratadine": "Allergy & Cold",
    "acetaminophen/chlorpheniramine/phenylephrine": "Allergy & Cold",
    "acetaminophen/diphenhydramine/phenylephrine": "Allergy & Cold",
    "acetaminophen/doxylamine/phenylephrine": "Allergy & Cold",
    "ibuprofen/chlorpheniramine/pseudoephedrine": "Allergy & Cold",
    "aspirin/chlorpheniramine/phenylephrine": "Allergy & Cold",
    "diphenhydramine": "Allergy & Cold",
    "brompheniramine": "Allergy & Cold",
    "carbinoxamine": "Allergy & Cold",
    "chlorpheniramine": "Allergy & Cold",
    "clemastine": "Allergy & Cold",
    "cyproheptadine": "Allergy & Cold",
    "dexchlorpheniramine": "Allergy & Cold",
    "dimenhydrinate": "Allergy & Cold",
    "triprolidine": "Allergy & Cold",
    "hydroxyzine": "Allergy & Cold",
    "promethazine": "Allergy & Cold",
    "loratadine": "Allergy & Cold",
    "fexofenadine": "Allergy & Cold",
    "cetirizine": "Allergy & Cold",
    "desloratadine": "Allergy & Cold",
    "levocetirizine": "Allergy & Cold",
    "acetaminophen/chlorpheniramine": "Allergy & Cold",
    "chlorpheniramine/dextromethorphan/phenylephrine": "Allergy & Cold",
    "diphenhydramine topical": "Allergy & Cold",
    "doxylamine": "Allergy & Cold",
    "dextromethorphan/phenylephrine/guaifenesin": "Allergy & Cold",
    "dextromethorphan/pseudoephedrine/guaifenesin": "Allergy & Cold",
    "dextromethorphan": "Allergy & Cold",
    "benzonatate": "Allergy & Cold",
    "codeine": "Allergy & Cold",
    "codeine/guaifenesin": "Allergy & Cold",
    "codeine/guaifenesin/pseudoephedrine": "Allergy & Cold",
    "chlorpheniramine/hydrocodone": "Allergy & Cold",
    "codeine/chlorpheniramine": "Allergy & Cold",
    "codeine/chlorpheniramine/phenylephrine": "Allergy & Cold",
    "codeine/chlorpheniramine/pseudoephedrine": "Allergy & Cold",
    "codeine/pseudoephedrine": "Allergy & Cold",
    "codeine/triprolidine/pseudoephedrine": "Allergy & Cold",
    "hydrocodone/guaifenesin": "Allergy & Cold",
    "hydrocodone/pseudoephedrine/guaifenesin": "Allergy & Cold",
    "hydrocodone/chlorpheniramine/pseudoephedrine": "Allergy & Cold",
    "hydrocodone/homatropine": "Allergy & Cold",
    "hydrocodone/pseudoephedrine": "Allergy & Cold",
    "promethazine/codeine/phenylephrine": "Allergy & Cold",
    "promethazine/codeine": "Allergy & Cold",
    "acetaminophen/doxylamine/dextromethorphan": "Allergy & Cold",
    "acetaminophen/pheniramine/phenylephrine": "Allergy & Cold",
    "aspirin/doxylamine/dextromethorphan/phenylephrine": "Allergy & Cold",
    "aspirin/diphenhydramine": "Allergy & Cold",
    "dextromethorphan/guaifenesin": "Allergy & Cold",
    "dextromethorphan/phenylephrine": "Allergy & Cold",
    "dextromethorphan/menthol": "Allergy & Cold",
    "doxylamine/dextromethorphan": "Allergy & Cold",
    "dyclonine/menthol": "Allergy & Cold",
    "menthol/pectin": "Allergy & Cold",
    "promethazine/dextromethorphan": "Allergy & Cold",
    "beclomethasone, intranasal": "Allergy & Cold",
    "budesonide intranasal": "Allergy & Cold",
    "fluticasone intranasal": "Allergy & Cold",
    "ciclesonide intranasal": "Allergy & Cold",
    "flunisolide intranasal": "Allergy & Cold",
    "mometasone, intranasal": "Allergy & Cold",
    "triamcinolone, intranasal": "Allergy & Cold",
    "acetaminophen/dextromethorphan": "Allergy & Cold",
    "acetaminophen/diphenhydramine": "Allergy & Cold",
    "acetaminophen/doxylamine/dextromethorphan/pseudoephedrine": "Allergy & Cold",
    "guaifenesin/pseudoephedrine": "Allergy & Cold",
    "phenylephrine/guaifenesin": "Allergy & Cold",
    "ephedrine/guaifenesin": "Allergy & Cold",
    "oxymetazoline intranasal": "Allergy & Cold",
    "sodium chloride, intranasal": "Allergy & Cold",
    "propylhexedrine": "Allergy & Cold",
    "hypotonic saline, intranasal": "Allergy & Cold",
    "naphazoline": "Allergy & Cold",
    "phenylephrine nasal": "Allergy & Cold",
    "xylometazoline": "Allergy & Cold",
    "pseudoephedrine": "Allergy & Cold",
    "phenylephrine PO": "Allergy & Cold",
    "guaifenesin": "Allergy & Cold",
    "potassium iodide": "Allergy & Cold"
}